isidore/__init__.py
isidore/libIsidore.py
isidore/libIsidoreCmdline.py
isidore-0.1.6.dist-info/LICENSE
isidore-0.1.6.dist-info/METADATA
isidore-0.1.6.dist-info/WHEEL
isidore-0.1.6.dist-info/top_level.txt
isidore-0.1.6.dist-info/RECORD
