Metadata-Version: 2.1
Name: isidore
Version: 0.1.6
Summary: database, API, and CLI suite for managing Ansible inventories
Author-email: Scott Court <Z5T1@Z5T1.com>
Project-URL: Homepage, https://github.com/Z5T1/isidore
Project-URL: Bug Tracker, https://github.com/Z5T1/isidore/issues
Project-URL: Documentation, https://github.com/Z5T1/isidore/blob/master/doc/README.md
Project-URL: Discord, https://discord.gg/c357N3JQFJ
Project-URL: Source Code, https://github.com/Z5T1/isidore
Keywords: ansible,inventory,database,isidore
Classifier: Programming Language :: Python :: 3
Classifier: License :: OSI Approved :: MIT License
Classifier: Operating System :: OS Independent
Requires-Python: >=3.7
License-File: LICENSE
Requires-Dist: mysql-connector-python
Requires-Dist: pyyaml
